nonebot_plugin_wiki/__init__.py
nonebot_plugin_wiki/config.py
nonebot_plugin_wiki/data.py
nonebot_plugin_wiki/handle.py
nonebot_plugin_wiki/utils.py
nonebot_plugin_wiki/SubCmd/__init__.py
nonebot_plugin_wiki/SubCmd/admin.py
nonebot_plugin_wiki/SubCmd/member.py
nonebot_plugin_wiki/SubCmd/utils.py
nonebot_plugin_wiki/mediawiki/__init__.py
nonebot_plugin_wiki/mediawiki/exceptions.py
nonebot_plugin_wiki/mediawiki/util.py
nonebot_plugin_wiki/mediawiki/wikipedia.py
nonebot_plugin_wiki-0.1.0.dist-info/LICENSE
nonebot_plugin_wiki-0.1.0.dist-info/METADATA
nonebot_plugin_wiki-0.1.0.dist-info/WHEEL
nonebot_plugin_wiki-0.1.0.dist-info/top_level.txt
nonebot_plugin_wiki-0.1.0.dist-info/RECORD
