Metadata-Version: 2.1
Name: nonebot-plugin-wiki
Version: 0.1.0
Summary: Nonebot2 插件，基于mediawiki api搜索条目
Home-page: https://github.com/ZombieFly/nb2-wiki
Author: ZombieFly
Author-email: xyzomfly@gmail.com
Classifier: Programming Language :: Python :: 3
Classifier: License :: OSI Approved :: MIT License
Classifier: Operating System :: OS Independent
License-File: LICENSE
Requires-Dist: beautifulsoup4
Requires-Dist: httpx
Requires-Dist: nonebot2 (>=2.0.0b1)
Requires-Dist: nonebot-adapter-onebot
